footballbot/__init__.py
footballbot-0.1.0.data/scripts/footballbot
footballbot-0.1.0.dist-info/LICENSE
footballbot-0.1.0.dist-info/METADATA
footballbot-0.1.0.dist-info/WHEEL
footballbot-0.1.0.dist-info/top_level.txt
footballbot-0.1.0.dist-info/RECORD
