Metadata-Version: 2.1
Name: footballbot
Version: 0.1.0
Summary: A kudubot that serves football information
Home-page: https://gitlab.namibsun.net/namibsun/python/footballbot
Author: Hermann Krumrey
Author-email: hermann@krumreyh.com
License: GNU GPL3
Platform: UNKNOWN
Classifier: License :: OSI Approved :: GNU General Public License v3 (GPLv3)
Requires-Dist: typing
Requires-Dist: requests
Requires-Dist: bokkichat
Requires-Dist: kudubot
Requires-Dist: sqlalchemy
